slackish/__init__.py
slackish/analytics.py
slackish/helpers.py
slackish/invites.py
slackish-0.4.0.dist-info/LICENSE
slackish-0.4.0.dist-info/METADATA
slackish-0.4.0.dist-info/WHEEL
slackish-0.4.0.dist-info/RECORD
