Metadata-Version: 2.1
Name: slackish
Version: 0.4.0
Summary: A Python module to access Slack's API from user-space, to circumvent all the artificial API limitations put in by greedy Salesforce. 🤑
License: Unlicense
Author: Jérémie Lumbroso
Author-email: lumbroso@seas.upenn.edu
Requires-Python: >=3.11,<4.0
Classifier: License :: OSI Approved
Classifier: Programming Language :: Python :: 3
Classifier: Programming Language :: Python :: 3.11
Requires-Dist: loguru (>=0.7.2,<0.8.0)
Requires-Dist: requests (>=2.31.0,<3.0.0)
